{
  "v": "5.7.4",
  "fr": 12,
  "ip": 0,
  "op": 36,
  "w": 400,
  "h": 400,
  "nm": "cooldown_shoulder_stretch",
  "ddd": 0,
  "assets": [],
  "fonts": {
    "list": []
  },
  "markers": [],
  "layers": [
    {
      "ty": 4,
      "nm": "head",
      "ind": 1,
      "ip": 0,
      "op": 36,
      "st": 0,
      "bm": 0,
      "sr": 1,
      "ks": {
        "p": {
          "a": 1,
          "k": [
            {
              "t": 0,
              "s": [
                210,
                195
              ],
              "i": {
                "x": [
                  0.42
                ],
                "y": [
                  1.0
                ]
              },
              "o": {
                "x": [
                  0.58
                ],
                "y": [
                  0.0
                ]
              }
            },
            {
              "t": 18,
              "s": [
                210,
                193
              ],
              "i": {
                "x": [
                  0.42
                ],
                "y": [
                  1.0
                ]
              },
              "o": {
                "x": [
                  0.58
                ],
                "y": [
                  0.0
                ]
              }
            },
            {
              "t": 36,
              "s": [
                210,
                195
              ]
            }
          ]
        },
        "r": {
          "a": 1,
          "k": [
            {
              "t": 0,
              "s": [
                3
              ],
              "i": {
                "x": [
                  0.42
                ],
                "y": [
                  1.0
                ]
              },
              "o": {
                "x": [
                  0.58
                ],
                "y": [
                  0.0
                ]
              }
            },
            {
              "t": 18,
              "s": [
                1
              ],
              "i": {
                "x": [
                  0.42
                ],
                "y": [
                  1.0
                ]
              },
              "o": {
                "x": [
                  0.58
                ],
                "y": [
                  0.0
                ]
              }
            },
            {
              "t": 36,
              "s": [
                3
              ]
            }
          ]
        },
        "a": {
          "a": 0,
          "k": [
            0,
            0
          ]
        },
        "s": {
          "a": 0,
          "k": [
            100,
            100
          ]
        },
        "o": {
          "a": 0,
          "k": 100
        }
      },
      "shapes": [
        {
          "ty": "gr",
          "nm": "crest",
          "it": [
            {
              "ty": "el",
              "s": {
                "a": 0,
                "k": [
                  20,
                  18
                ]
              },
              "p": {
                "a": 0,
                "k": [
                  -2,
                  -30
                ]
              },
              "nm": "el",
              "d": 1
            },
            {
              "ty": "fl",
              "c": {
                "a": 0,
                "k": [
                  0.2196078431372549,
                  0.2196078431372549,
                  0.2980392156862745,
                  1.0
                ]
              },
              "o": {
                "a": 0,
                "k": 100
              },
              "r": 1,
              "nm": "fill"
            },
            {
              "ty": "tr",
              "p": {
                "a": 0,
                "k": [
                  0,
                  0
                ]
              },
              "r": {
                "a": 0,
                "k": 0
              },
              "s": {
                "a": 0,
                "k": [
                  100,
                  100
                ]
              },
              "a": {
                "a": 0,
                "k": [
                  0,
                  0
                ]
              },
              "o": {
                "a": 0,
                "k": 100
              },
              "sk": {
                "a": 0,
                "k": 0
              },
              "sa": {
                "a": 0,
                "k": 0
              },
              "nm": "tr"
            }
          ],
          "np": 3,
          "cix": 2,
          "ix": 1
        },
        {
          "ty": "gr",
          "nm": "brow",
          "it": [
            {
              "ty": "rc",
              "s": {
                "a": 0,
                "k": [
                  50,
                  12
                ]
              },
              "p": {
                "a": 0,
                "k": [
                  3,
                  -14
                ]
              },
              "r": {
                "a": 0,
                "k": 4
              },
              "nm": "rc",
              "d": 1
            },
            {
              "ty": "fl",
              "c": {
                "a": 0,
                "k": [
                  0.2196078431372549,
                  0.2196078431372549,
                  0.2980392156862745,
                  1.0
                ]
              },
              "o": {
                "a": 0,
                "k": 100
              },
              "r": 1,
              "nm": "fill"
            },
            {
              "ty": "tr",
              "p": {
                "a": 0,
                "k": [
                  0,
                  0
                ]
              },
              "r": {
                "a": 0,
                "k": 0
              },
              "s": {
                "a": 0,
                "k": [
                  100,
                  100
                ]
              },
              "a": {
                "a": 0,
                "k": [
                  0,
                  0
                ]
              },
              "o": {
                "a": 0,
                "k": 100
              },
              "sk": {
                "a": 0,
                "k": 0
              },
              "sa": {
                "a": 0,
                "k": 0
              },
              "nm": "tr"
            }
          ],
          "np": 3,
          "cix": 2,
          "ix": 1
        },
        {
          "ty": "gr",
          "nm": "face",
          "it": [
            {
              "ty": "el",
              "s": {
                "a": 0,
                "k": [
                  38,
                  42
                ]
              },
              "p": {
                "a": 0,
                "k": [
                  10,
                  6
                ]
              },
              "nm": "el",
              "d": 1
            },
            {
              "ty": "fl",
              "c": {
                "a": 0,
                "k": [
                  0.7686274509803922,
                  0.6588235294117647,
                  0.5098039215686274,
                  1.0
                ]
              },
              "o": {
                "a": 0,
                "k": 100
              },
              "r": 1,
              "nm": "fill"
            },
            {
              "ty": "tr",
              "p": {
                "a": 0,
                "k": [
                  0,
                  0
                ]
              },
              "r": {
                "a": 0,
                "k": 0
              },
              "s": {
                "a": 0,
                "k": [
                  100,
                  100
                ]
              },
              "a": {
                "a": 0,
                "k": [
                  0,
                  0
                ]
              },
              "o": {
                "a": 0,
                "k": 100
              },
              "sk": {
                "a": 0,
                "k": 0
              },
              "sa": {
                "a": 0,
                "k": 0
              },
              "nm": "tr"
            }
          ],
          "np": 3,
          "cix": 2,
          "ix": 1
        },
        {
          "ty": "gr",
          "nm": "headband",
          "it": [
            {
              "ty": "rc",
              "s": {
                "a": 0,
                "k": [
                  62,
                  9
                ]
              },
              "p": {
                "a": 0,
                "k": [
                  0,
                  -16
                ]
              },
              "r": {
                "a": 0,
                "k": 3
              },
              "nm": "rc",
              "d": 1
            },
            {
              "ty": "fl",
              "c": {
                "a": 0,
                "k": [
                  0.6588235294117647,
                  0.8470588235294118,
                  1.0,
                  1.0
                ]
              },
              "o": {
                "a": 0,
                "k": 100
              },
              "r": 1,
              "nm": "fill"
            },
            {
              "ty": "tr",
              "p": {
                "a": 0,
                "k": [
                  0,
                  0
                ]
              },
              "r": {
                "a": 0,
                "k": 0
              },
              "s": {
                "a": 0,
                "k": [
                  100,
                  100
                ]
              },
              "a": {
                "a": 0,
                "k": [
                  0,
                  0
                ]
              },
              "o": {
                "a": 0,
                "k": 100
              },
              "sk": {
                "a": 0,
                "k": 0
              },
              "sa": {
                "a": 0,
                "k": 0
              },
              "nm": "tr"
            }
          ],
          "np": 3,
          "cix": 2,
          "ix": 1
        },
        {
          "ty": "gr",
          "nm": "shine",
          "it": [
            {
              "ty": "rc",
              "s": {
                "a": 0,
                "k": [
                  44,
                  4
                ]
              },
              "p": {
                "a": 0,
                "k": [
                  0,
                  -17
                ]
              },
              "r": {
                "a": 0,
                "k": 2
              },
              "nm": "rc",
              "d": 1
            },
            {
              "ty": "fl",
              "c": {
                "a": 0,
                "k": [
                  1.0,
                  1.0,
                  1.0,
                  1.0
                ]
              },
              "o": {
                "a": 0,
                "k": 100
              },
              "r": 1,
              "nm": "fill"
            },
            {
              "ty": "tr",
              "p": {
                "a": 0,
                "k": [
                  0,
                  0
                ]
              },
              "r": {
                "a": 0,
                "k": 0
              },
              "s": {
                "a": 0,
                "k": [
                  100,
                  100
                ]
              },
              "a": {
                "a": 0,
                "k": [
                  0,
                  0
                ]
              },
              "o": {
                "a": 0,
                "k": 100
              },
              "sk": {
                "a": 0,
                "k": 0
              },
              "sa": {
                "a": 0,
                "k": 0
              },
              "nm": "tr"
            }
          ],
          "np": 3,
          "cix": 2,
          "ix": 1
        },
        {
          "ty": "gr",
          "nm": "nose",
          "it": [
            {
              "ty": "el",
              "s": {
                "a": 0,
                "k": [
                  18,
                  12
                ]
              },
              "p": {
                "a": 0,
                "k": [
                  13,
                  9
                ]
              },
              "nm": "el",
              "d": 1
            },
            {
              "ty": "fl",
              "c": {
                "a": 0,
                "k": [
                  0.5882352941176471,
                  0.4666666666666667,
                  0.33725490196078434,
                  1.0
                ]
              },
              "o": {
                "a": 0,
                "k": 100
              },
              "r": 1,
              "nm": "fill"
            },
            {
              "ty": "tr",
              "p": {
                "a": 0,
                "k": [
                  0,
                  0
                ]
              },
              "r": {
                "a": 0,
                "k": 0
              },
              "s": {
                "a": 0,
                "k": [
                  100,
                  100
                ]
              },
              "a": {
                "a": 0,
                "k": [
                  0,
                  0
                ]
              },
              "o": {
                "a": 0,
                "k": 100
              },
              "sk": {
                "a": 0,
                "k": 0
              },
              "sa": {
                "a": 0,
                "k": 0
              },
              "nm": "tr"
            }
          ],
          "np": 3,
          "cix": 2,
          "ix": 1
        },
        {
          "ty": "gr",
          "nm": "nos_l",
          "it": [
            {
              "ty": "el",
              "s": {
                "a": 0,
                "k": [
                  6,
                  5
                ]
              },
              "p": {
                "a": 0,
                "k": [
                  10,
                  11
                ]
              },
              "nm": "el",
              "d": 1
            },
            {
              "ty": "fl",
              "c": {
                "a": 0,
                "k": [
                  0.47843137254901963,
                  0.3764705882352941,
                  0.27058823529411763,
                  1.0
                ]
              },
              "o": {
                "a": 0,
                "k": 100
              },
              "r": 1,
              "nm": "fill"
            },
            {
              "ty": "tr",
              "p": {
                "a": 0,
                "k": [
                  0,
                  0
                ]
              },
              "r": {
                "a": 0,
                "k": 0
              },
              "s": {
                "a": 0,
                "k": [
                  100,
                  100
                ]
              },
              "a": {
                "a": 0,
                "k": [
                  0,
                  0
                ]
              },
              "o": {
                "a": 0,
                "k": 100
              },
              "sk": {
                "a": 0,
                "k": 0
              },
              "sa": {
                "a": 0,
                "k": 0
              },
              "nm": "tr"
            }
          ],
          "np": 3,
          "cix": 2,
          "ix": 1
        },
        {
          "ty": "gr",
          "nm": "nos_r",
          "it": [
            {
              "ty": "el",
              "s": {
                "a": 0,
                "k": [
                  6,
                  5
                ]
              },
              "p": {
                "a": 0,
                "k": [
                  17,
                  11
                ]
              },
              "nm": "el",
              "d": 1
            },
            {
              "ty": "fl",
              "c": {
                "a": 0,
                "k": [
                  0.47843137254901963,
                  0.3764705882352941,
                  0.27058823529411763,
                  1.0
                ]
              },
              "o": {
                "a": 0,
                "k": 100
              },
              "r": 1,
              "nm": "fill"
            },
            {
              "ty": "tr",
              "p": {
                "a": 0,
                "k": [
                  0,
                  0
                ]
              },
              "r": {
                "a": 0,
                "k": 0
              },
              "s": {
                "a": 0,
                "k": [
                  100,
                  100
                ]
              },
              "a": {
                "a": 0,
                "k": [
                  0,
                  0
                ]
              },
              "o": {
                "a": 0,
                "k": 100
              },
              "sk": {
                "a": 0,
                "k": 0
              },
              "sa": {
                "a": 0,
                "k": 0
              },
              "nm": "tr"
            }
          ],
          "np": 3,
          "cix": 2,
          "ix": 1
        },
        {
          "ty": "gr",
          "nm": "eye_w",
          "it": [
            {
              "ty": "el",
              "s": {
                "a": 0,
                "k": [
                  14,
                  12
                ]
              },
              "p": {
                "a": 0,
                "k": [
                  10,
                  -3
                ]
              },
              "nm": "el",
              "d": 1
            },
            {
              "ty": "fl",
              "c": {
                "a": 0,
                "k": [
                  1.0,
                  1.0,
                  1.0,
                  1.0
                ]
              },
              "o": {
                "a": 0,
                "k": 100
              },
              "r": 1,
              "nm": "fill"
            },
            {
              "ty": "tr",
              "p": {
                "a": 0,
                "k": [
                  0,
                  0
                ]
              },
              "r": {
                "a": 0,
                "k": 0
              },
              "s": {
                "a": 0,
                "k": [
                  100,
                  100
                ]
              },
              "a": {
                "a": 0,
                "k": [
                  0,
                  0
                ]
              },
              "o": {
                "a": 0,
                "k": 100
              },
              "sk": {
                "a": 0,
                "k": 0
              },
              "sa": {
                "a": 0,
                "k": 0
              },
              "nm": "tr"
            }
          ],
          "np": 3,
          "cix": 2,
          "ix": 1
        },
        {
          "ty": "gr",
          "nm": "eye_p",
          "it": [
            {
              "ty": "el",
              "s": {
                "a": 0,
                "k": [
                  7,
                  8
                ]
              },
              "p": {
                "a": 0,
                "k": [
                  10,
                  -3
                ]
              },
              "nm": "el",
              "d": 1
            },
            {
              "ty": "fl",
              "c": {
                "a": 0,
                "k": [
                  0.10196078431372549,
                  0.10196078431372549,
                  0.16470588235294117,
                  1.0
                ]
              },
              "o": {
                "a": 0,
                "k": 100
              },
              "r": 1,
              "nm": "fill"
            },
            {
              "ty": "tr",
              "p": {
                "a": 0,
                "k": [
                  0,
                  0
                ]
              },
              "r": {
                "a": 0,
                "k": 0
              },
              "s": {
                "a": 0,
                "k": [
                  100,
                  100
                ]
              },
              "a": {
                "a": 0,
                "k": [
                  0,
                  0
                ]
              },
              "o": {
                "a": 0,
                "k": 100
              },
              "sk": {
                "a": 0,
                "k": 0
              },
              "sa": {
                "a": 0,
                "k": 0
              },
              "nm": "tr"
            }
          ],
          "np": 3,
          "cix": 2,
          "ix": 1
        },
        {
          "ty": "gr",
          "nm": "eye_s",
          "it": [
            {
              "ty": "el",
              "s": {
                "a": 0,
                "k": [
                  3.5,
                  3.5
                ]
              },
              "p": {
                "a": 0,
                "k": [
                  12,
                  -5
                ]
              },
              "nm": "el",
              "d": 1
            },
            {
              "ty": "fl",
              "c": {
                "a": 0,
                "k": [
                  1.0,
                  1.0,
                  1.0,
                  1.0
                ]
              },
              "o": {
                "a": 0,
                "k": 100
              },
              "r": 1,
              "nm": "fill"
            },
            {
              "ty": "tr",
              "p": {
                "a": 0,
                "k": [
                  0,
                  0
                ]
              },
              "r": {
                "a": 0,
                "k": 0
              },
              "s": {
                "a": 0,
                "k": [
                  100,
                  100
                ]
              },
              "a": {
                "a": 0,
                "k": [
                  0,
                  0
                ]
              },
              "o": {
                "a": 0,
                "k": 100
              },
              "sk": {
                "a": 0,
                "k": 0
              },
              "sa": {
                "a": 0,
                "k": 0
              },
              "nm": "tr"
            }
          ],
          "np": 3,
          "cix": 2,
          "ix": 1
        },
        {
          "ty": "gr",
          "nm": "ear",
          "it": [
            {
              "ty": "el",
              "s": {
                "a": 0,
                "k": [
                  12,
                  16
                ]
              },
              "p": {
                "a": 0,
                "k": [
                  -20,
                  4
                ]
              },
              "nm": "el",
              "d": 1
            },
            {
              "ty": "fl",
              "c": {
                "a": 0,
                "k": [
                  0.2196078431372549,
                  0.2196078431372549,
                  0.2980392156862745,
                  1.0
                ]
              },
              "o": {
                "a": 0,
                "k": 100
              },
              "r": 1,
              "nm": "fill"
            },
            {
              "ty": "tr",
              "p": {
                "a": 0,
                "k": [
                  0,
                  0
                ]
              },
              "r": {
                "a": 0,
                "k": 0
              },
              "s": {
                "a": 0,
                "k": [
                  100,
                  100
                ]
              },
              "a": {
                "a": 0,
                "k": [
                  0,
                  0
                ]
              },
              "o": {
                "a": 0,
                "k": 100
              },
              "sk": {
                "a": 0,
                "k": 0
              },
              "sa": {
                "a": 0,
                "k": 0
              },
              "nm": "tr"
            }
          ],
          "np": 3,
          "cix": 2,
          "ix": 1
        },
        {
          "ty": "gr",
          "nm": "ear_in",
          "it": [
            {
              "ty": "el",
              "s": {
                "a": 0,
                "k": [
                  7,
                  10
                ]
              },
              "p": {
                "a": 0,
                "k": [
                  -20,
                  5
                ]
              },
              "nm": "el",
              "d": 1
            },
            {
              "ty": "fl",
              "c": {
                "a": 0,
                "k": [
                  0.7686274509803922,
                  0.6588235294117647,
                  0.5098039215686274,
                  1.0
                ]
              },
              "o": {
                "a": 0,
                "k": 100
              },
              "r": 1,
              "nm": "fill"
            },
            {
              "ty": "tr",
              "p": {
                "a": 0,
                "k": [
                  0,
                  0
                ]
              },
              "r": {
                "a": 0,
                "k": 0
              },
              "s": {
                "a": 0,
                "k": [
                  100,
                  100
                ]
              },
              "a": {
                "a": 0,
                "k": [
                  0,
                  0
                ]
              },
              "o": {
                "a": 0,
                "k": 100
              },
              "sk": {
                "a": 0,
                "k": 0
              },
              "sa": {
                "a": 0,
                "k": 0
              },
              "nm": "tr"
            }
          ],
          "np": 3,
          "cix": 2,
          "ix": 1
        },
        {
          "ty": "gr",
          "nm": "skull",
          "it": [
            {
              "ty": "el",
              "s": {
                "a": 0,
                "k": [
                  58,
                  58
                ]
              },
              "p": {
                "a": 0,
                "k": [
                  0,
                  0
                ]
              },
              "nm": "el",
              "d": 1
            },
            {
              "ty": "fl",
              "c": {
                "a": 0,
                "k": [
                  0.2196078431372549,
                  0.2196078431372549,
                  0.2980392156862745,
                  1.0
                ]
              },
              "o": {
                "a": 0,
                "k": 100
              },
              "r": 1,
              "nm": "fill"
            },
            {
              "ty": "tr",
              "p": {
                "a": 0,
                "k": [
                  0,
                  0
                ]
              },
              "r": {
                "a": 0,
                "k": 0
              },
              "s": {
                "a": 0,
                "k": [
                  100,
                  100
                ]
              },
              "a": {
                "a": 0,
                "k": [
                  0,
                  0
                ]
              },
              "o": {
                "a": 0,
                "k": 100
              },
              "sk": {
                "a": 0,
                "k": 0
              },
              "sa": {
                "a": 0,
                "k": 0
              },
              "nm": "tr"
            }
          ],
          "np": 3,
          "cix": 2,
          "ix": 1
        }
      ],
      "ao": 0
    },
    {
      "ty": 4,
      "nm": "arm_far",
      "ind": 16,
      "ip": 0,
      "op": 36,
      "st": 0,
      "bm": 0,
      "sr": 1,
      "ao": 0,
      "ks": {
        "p": {
          "a": 0,
          "k": [
            178,
            228
          ]
        },
        "r": {
          "a": 1,
          "k": [
            {
              "t": 0,
              "s": [
                90
              ],
              "i": {
                "x": [
                  0.42
                ],
                "y": [
                  1.0
                ]
              },
              "o": {
                "x": [
                  0.58
                ],
                "y": [
                  0.0
                ]
              }
            },
            {
              "t": 18,
              "s": [
                95
              ],
              "i": {
                "x": [
                  0.42
                ],
                "y": [
                  1.0
                ]
              },
              "o": {
                "x": [
                  0.58
                ],
                "y": [
                  0.0
                ]
              }
            },
            {
              "t": 36,
              "s": [
                90
              ]
            }
          ]
        },
        "a": {
          "a": 0,
          "k": [
            0,
            -39.0
          ]
        },
        "s": {
          "a": 0,
          "k": [
            100,
            100
          ]
        },
        "o": {
          "a": 0,
          "k": 60
        }
      },
      "shapes": [
        {
          "ty": "gr",
          "nm": "arm",
          "it": [
            {
              "ty": "rc",
              "s": {
                "a": 0,
                "k": [
                  16,
                  78
                ]
              },
              "p": {
                "a": 0,
                "k": [
                  0,
                  0
                ]
              },
              "r": {
                "a": 0,
                "k": 5
              },
              "nm": "rc",
              "d": 1
            },
            {
              "ty": "el",
              "s": {
                "a": 0,
                "k": [
                  20,
                  14
                ]
              },
              "p": {
                "a": 0,
                "k": [
                  0,
                  47.0
                ]
              },
              "nm": "el",
              "d": 1
            },
            {
              "ty": "fl",
              "c": {
                "a": 0,
                "k": [
                  0.25882352941176473,
                  0.25882352941176473,
                  0.34509803921568627,
                  1.0
                ]
              },
              "o": {
                "a": 0,
                "k": 100
              },
              "r": 1,
              "nm": "fill"
            },
            {
              "ty": "tr",
              "p": {
                "a": 0,
                "k": [
                  0,
                  0
                ]
              },
              "r": {
                "a": 0,
                "k": 0
              },
              "s": {
                "a": 0,
                "k": [
                  100,
                  100
                ]
              },
              "a": {
                "a": 0,
                "k": [
                  0,
                  0
                ]
              },
              "o": {
                "a": 0,
                "k": 100
              },
              "sk": {
                "a": 0,
                "k": 0
              },
              "sa": {
                "a": 0,
                "k": 0
              },
              "nm": "tr"
            }
          ],
          "np": 4,
          "cix": 2,
          "ix": 1
        }
      ]
    },
    {
      "ty": 4,
      "nm": "body",
      "ind": 4,
      "ip": 0,
      "op": 36,
      "st": 0,
      "bm": 0,
      "sr": 1,
      "ks": {
        "p": {
          "a": 1,
          "k": [
            {
              "t": 0,
              "s": [
                192,
                268
              ],
              "i": {
                "x": [
                  0.42
                ],
                "y": [
                  1.0
                ]
              },
              "o": {
                "x": [
                  0.58
                ],
                "y": [
                  0.0
                ]
              }
            },
            {
              "t": 18,
              "s": [
                192,
                267
              ],
              "i": {
                "x": [
                  0.42
                ],
                "y": [
                  1.0
                ]
              },
              "o": {
                "x": [
                  0.58
                ],
                "y": [
                  0.0
                ]
              }
            },
            {
              "t": 36,
              "s": [
                192,
                268
              ]
            }
          ]
        },
        "r": {
          "a": 1,
          "k": [
            {
              "t": 0,
              "s": [
                4
              ],
              "i": {
                "x": [
                  0.42
                ],
                "y": [
                  1.0
                ]
              },
              "o": {
                "x": [
                  0.58
                ],
                "y": [
                  0.0
                ]
              }
            },
            {
              "t": 18,
              "s": [
                6
              ],
              "i": {
                "x": [
                  0.42
                ],
                "y": [
                  1.0
                ]
              },
              "o": {
                "x": [
                  0.58
                ],
                "y": [
                  0.0
                ]
              }
            },
            {
              "t": 36,
              "s": [
                4
              ]
            }
          ]
        },
        "a": {
          "a": 0,
          "k": [
            0,
            0
          ]
        },
        "s": {
          "a": 0,
          "k": [
            100,
            100
          ]
        },
        "o": {
          "a": 0,
          "k": 100
        }
      },
      "shapes": [
        {
          "ty": "gr",
          "nm": "torso",
          "it": [
            {
              "ty": "rc",
              "s": {
                "a": 0,
                "k": [
                  56,
                  100
                ]
              },
              "p": {
                "a": 0,
                "k": [
                  0,
                  0
                ]
              },
              "r": {
                "a": 0,
                "k": 5
              },
              "nm": "rc",
              "d": 1
            },
            {
              "ty": "fl",
              "c": {
                "a": 0,
                "k": [
                  0.2196078431372549,
                  0.2196078431372549,
                  0.2980392156862745,
                  1.0
                ]
              },
              "o": {
                "a": 0,
                "k": 100
              },
              "r": 1,
              "nm": "fill"
            },
            {
              "ty": "tr",
              "p": {
                "a": 0,
                "k": [
                  0,
                  0
                ]
              },
              "r": {
                "a": 0,
                "k": 0
              },
              "s": {
                "a": 0,
                "k": [
                  100,
                  100
                ]
              },
              "a": {
                "a": 0,
                "k": [
                  0,
                  0
                ]
              },
              "o": {
                "a": 0,
                "k": 100
              },
              "sk": {
                "a": 0,
                "k": 0
              },
              "sa": {
                "a": 0,
                "k": 0
              },
              "nm": "tr"
            }
          ],
          "np": 3,
          "cix": 2,
          "ix": 1
        },
        {
          "ty": "gr",
          "nm": "chest",
          "it": [
            {
              "ty": "rc",
              "s": {
                "a": 0,
                "k": [
                  42,
                  16
                ]
              },
              "p": {
                "a": 0,
                "k": [
                  0,
                  -30
                ]
              },
              "r": {
                "a": 0,
                "k": 4
              },
              "nm": "rc",
              "d": 1
            },
            {
              "ty": "fl",
              "c": {
                "a": 0,
                "k": [
                  0.25882352941176473,
                  0.25882352941176473,
                  0.34509803921568627,
                  1.0
                ]
              },
              "o": {
                "a": 0,
                "k": 100
              },
              "r": 1,
              "nm": "fill"
            },
            {
              "ty": "tr",
              "p": {
                "a": 0,
                "k": [
                  0,
                  0
                ]
              },
              "r": {
                "a": 0,
                "k": 0
              },
              "s": {
                "a": 0,
                "k": [
                  100,
                  100
                ]
              },
              "a": {
                "a": 0,
                "k": [
                  0,
                  0
                ]
              },
              "o": {
                "a": 0,
                "k": 100
              },
              "sk": {
                "a": 0,
                "k": 0
              },
              "sa": {
                "a": 0,
                "k": 0
              },
              "nm": "tr"
            }
          ],
          "np": 3,
          "cix": 2,
          "ix": 1
        },
        {
          "ty": "gr",
          "nm": "abs",
          "it": [
            {
              "ty": "rc",
              "s": {
                "a": 0,
                "k": [
                  36,
                  10
                ]
              },
              "p": {
                "a": 0,
                "k": [
                  0,
                  6
                ]
              },
              "r": {
                "a": 0,
                "k": 3
              },
              "nm": "rc",
              "d": 1
            },
            {
              "ty": "fl",
              "c": {
                "a": 0,
                "k": [
                  0.25882352941176473,
                  0.25882352941176473,
                  0.34509803921568627,
                  1.0
                ]
              },
              "o": {
                "a": 0,
                "k": 100
              },
              "r": 1,
              "nm": "fill"
            },
            {
              "ty": "tr",
              "p": {
                "a": 0,
                "k": [
                  0,
                  0
                ]
              },
              "r": {
                "a": 0,
                "k": 0
              },
              "s": {
                "a": 0,
                "k": [
                  100,
                  100
                ]
              },
              "a": {
                "a": 0,
                "k": [
                  0,
                  0
                ]
              },
              "o": {
                "a": 0,
                "k": 100
              },
              "sk": {
                "a": 0,
                "k": 0
              },
              "sa": {
                "a": 0,
                "k": 0
              },
              "nm": "tr"
            }
          ],
          "np": 3,
          "cix": 2,
          "ix": 1
        }
      ],
      "ao": 0
    },
    {
      "ty": 4,
      "nm": "arm_near",
      "ind": 17,
      "ip": 0,
      "op": 36,
      "st": 0,
      "bm": 0,
      "sr": 1,
      "ao": 0,
      "ks": {
        "p": {
          "a": 0,
          "k": [
            185,
            225
          ]
        },
        "r": {
          "a": 1,
          "k": [
            {
              "t": 0,
              "s": [
                90
              ],
              "i": {
                "x": [
                  0.42
                ],
                "y": [
                  1.0
                ]
              },
              "o": {
                "x": [
                  0.58
                ],
                "y": [
                  0.0
                ]
              }
            },
            {
              "t": 18,
              "s": [
                95
              ],
              "i": {
                "x": [
                  0.42
                ],
                "y": [
                  1.0
                ]
              },
              "o": {
                "x": [
                  0.58
                ],
                "y": [
                  0.0
                ]
              }
            },
            {
              "t": 36,
              "s": [
                90
              ]
            }
          ]
        },
        "a": {
          "a": 0,
          "k": [
            0,
            -39.0
          ]
        },
        "s": {
          "a": 0,
          "k": [
            100,
            100
          ]
        },
        "o": {
          "a": 0,
          "k": 100
        }
      },
      "shapes": [
        {
          "ty": "gr",
          "nm": "arm",
          "it": [
            {
              "ty": "rc",
              "s": {
                "a": 0,
                "k": [
                  16,
                  78
                ]
              },
              "p": {
                "a": 0,
                "k": [
                  0,
                  0
                ]
              },
              "r": {
                "a": 0,
                "k": 5
              },
              "nm": "rc",
              "d": 1
            },
            {
              "ty": "el",
              "s": {
                "a": 0,
                "k": [
                  20,
                  14
                ]
              },
              "p": {
                "a": 0,
                "k": [
                  0,
                  47.0
                ]
              },
              "nm": "el",
              "d": 1
            },
            {
              "ty": "fl",
              "c": {
                "a": 0,
                "k": [
                  0.2901960784313726,
                  0.2901960784313726,
                  0.3843137254901961,
                  1.0
                ]
              },
              "o": {
                "a": 0,
                "k": 100
              },
              "r": 1,
              "nm": "fill"
            },
            {
              "ty": "tr",
              "p": {
                "a": 0,
                "k": [
                  0,
                  0
                ]
              },
              "r": {
                "a": 0,
                "k": 0
              },
              "s": {
                "a": 0,
                "k": [
                  100,
                  100
                ]
              },
              "a": {
                "a": 0,
                "k": [
                  0,
                  0
                ]
              },
              "o": {
                "a": 0,
                "k": 100
              },
              "sk": {
                "a": 0,
                "k": 0
              },
              "sa": {
                "a": 0,
                "k": 0
              },
              "nm": "tr"
            }
          ],
          "np": 4,
          "cix": 2,
          "ix": 1
        }
      ]
    },
    {
      "ty": 4,
      "nm": "thigh_r",
      "ind": 8,
      "ip": 0,
      "op": 36,
      "st": 0,
      "bm": 0,
      "sr": 1,
      "ks": {
        "p": {
          "a": 0,
          "k": [
            192,
            326
          ]
        },
        "r": {
          "a": 0,
          "k": 0
        },
        "a": {
          "a": 0,
          "k": [
            0,
            0
          ]
        },
        "s": {
          "a": 0,
          "k": [
            100,
            100
          ]
        },
        "o": {
          "a": 0,
          "k": 100
        }
      },
      "shapes": [
        {
          "ty": "gr",
          "nm": "seg",
          "it": [
            {
              "ty": "rc",
              "s": {
                "a": 0,
                "k": [
                  28,
                  46
                ]
              },
              "p": {
                "a": 0,
                "k": [
                  0,
                  0
                ]
              },
              "r": {
                "a": 0,
                "k": 5
              },
              "nm": "rc",
              "d": 1
            },
            {
              "ty": "fl",
              "c": {
                "a": 0,
                "k": [
                  0.2196078431372549,
                  0.2196078431372549,
                  0.2980392156862745,
                  1.0
                ]
              },
              "o": {
                "a": 0,
                "k": 100
              },
              "r": 1,
              "nm": "fill"
            },
            {
              "ty": "tr",
              "p": {
                "a": 0,
                "k": [
                  0,
                  0
                ]
              },
              "r": {
                "a": 0,
                "k": 0
              },
              "s": {
                "a": 0,
                "k": [
                  100,
                  100
                ]
              },
              "a": {
                "a": 0,
                "k": [
                  0,
                  0
                ]
              },
              "o": {
                "a": 0,
                "k": 100
              },
              "sk": {
                "a": 0,
                "k": 0
              },
              "sa": {
                "a": 0,
                "k": 0
              },
              "nm": "tr"
            }
          ],
          "np": 3,
          "cix": 2,
          "ix": 1
        }
      ],
      "ao": 0
    },
    {
      "ty": 4,
      "nm": "shin_r",
      "ind": 9,
      "ip": 0,
      "op": 36,
      "st": 0,
      "bm": 0,
      "sr": 1,
      "ks": {
        "p": {
          "a": 0,
          "k": [
            190,
            358
          ]
        },
        "r": {
          "a": 0,
          "k": 0
        },
        "a": {
          "a": 0,
          "k": [
            0,
            0
          ]
        },
        "s": {
          "a": 0,
          "k": [
            100,
            100
          ]
        },
        "o": {
          "a": 0,
          "k": 100
        }
      },
      "shapes": [
        {
          "ty": "gr",
          "nm": "seg",
          "it": [
            {
              "ty": "rc",
              "s": {
                "a": 0,
                "k": [
                  22,
                  38
                ]
              },
              "p": {
                "a": 0,
                "k": [
                  0,
                  0
                ]
              },
              "r": {
                "a": 0,
                "k": 5
              },
              "nm": "rc",
              "d": 1
            },
            {
              "ty": "fl",
              "c": {
                "a": 0,
                "k": [
                  0.2196078431372549,
                  0.2196078431372549,
                  0.2980392156862745,
                  1.0
                ]
              },
              "o": {
                "a": 0,
                "k": 100
              },
              "r": 1,
              "nm": "fill"
            },
            {
              "ty": "tr",
              "p": {
                "a": 0,
                "k": [
                  0,
                  0
                ]
              },
              "r": {
                "a": 0,
                "k": 0
              },
              "s": {
                "a": 0,
                "k": [
                  100,
                  100
                ]
              },
              "a": {
                "a": 0,
                "k": [
                  0,
                  0
                ]
              },
              "o": {
                "a": 0,
                "k": 100
              },
              "sk": {
                "a": 0,
                "k": 0
              },
              "sa": {
                "a": 0,
                "k": 0
              },
              "nm": "tr"
            }
          ],
          "np": 3,
          "cix": 2,
          "ix": 1
        }
      ],
      "ao": 0
    },
    {
      "ty": 4,
      "nm": "thigh_l",
      "ind": 10,
      "ip": 0,
      "op": 36,
      "st": 0,
      "bm": 0,
      "sr": 1,
      "ks": {
        "p": {
          "a": 0,
          "k": [
            184,
            326
          ]
        },
        "r": {
          "a": 0,
          "k": 0
        },
        "a": {
          "a": 0,
          "k": [
            0,
            0
          ]
        },
        "s": {
          "a": 0,
          "k": [
            100,
            100
          ]
        },
        "o": {
          "a": 0,
          "k": 100
        }
      },
      "shapes": [
        {
          "ty": "gr",
          "nm": "seg",
          "it": [
            {
              "ty": "rc",
              "s": {
                "a": 0,
                "k": [
                  26,
                  44
                ]
              },
              "p": {
                "a": 0,
                "k": [
                  0,
                  0
                ]
              },
              "r": {
                "a": 0,
                "k": 5
              },
              "nm": "rc",
              "d": 1
            },
            {
              "ty": "fl",
              "c": {
                "a": 0,
                "k": [
                  0.25882352941176473,
                  0.25882352941176473,
                  0.34509803921568627,
                  1.0
                ]
              },
              "o": {
                "a": 0,
                "k": 100
              },
              "r": 1,
              "nm": "fill"
            },
            {
              "ty": "tr",
              "p": {
                "a": 0,
                "k": [
                  0,
                  0
                ]
              },
              "r": {
                "a": 0,
                "k": 0
              },
              "s": {
                "a": 0,
                "k": [
                  100,
                  100
                ]
              },
              "a": {
                "a": 0,
                "k": [
                  0,
                  0
                ]
              },
              "o": {
                "a": 0,
                "k": 100
              },
              "sk": {
                "a": 0,
                "k": 0
              },
              "sa": {
                "a": 0,
                "k": 0
              },
              "nm": "tr"
            }
          ],
          "np": 3,
          "cix": 2,
          "ix": 1
        }
      ],
      "ao": 0
    },
    {
      "ty": 4,
      "nm": "shin_l",
      "ind": 11,
      "ip": 0,
      "op": 36,
      "st": 0,
      "bm": 0,
      "sr": 1,
      "ks": {
        "p": {
          "a": 0,
          "k": [
            182,
            358
          ]
        },
        "r": {
          "a": 0,
          "k": 0
        },
        "a": {
          "a": 0,
          "k": [
            0,
            0
          ]
        },
        "s": {
          "a": 0,
          "k": [
            100,
            100
          ]
        },
        "o": {
          "a": 0,
          "k": 100
        }
      },
      "shapes": [
        {
          "ty": "gr",
          "nm": "seg",
          "it": [
            {
              "ty": "rc",
              "s": {
                "a": 0,
                "k": [
                  20,
                  36
                ]
              },
              "p": {
                "a": 0,
                "k": [
                  0,
                  0
                ]
              },
              "r": {
                "a": 0,
                "k": 5
              },
              "nm": "rc",
              "d": 1
            },
            {
              "ty": "fl",
              "c": {
                "a": 0,
                "k": [
                  0.25882352941176473,
                  0.25882352941176473,
                  0.34509803921568627,
                  1.0
                ]
              },
              "o": {
                "a": 0,
                "k": 100
              },
              "r": 1,
              "nm": "fill"
            },
            {
              "ty": "tr",
              "p": {
                "a": 0,
                "k": [
                  0,
                  0
                ]
              },
              "r": {
                "a": 0,
                "k": 0
              },
              "s": {
                "a": 0,
                "k": [
                  100,
                  100
                ]
              },
              "a": {
                "a": 0,
                "k": [
                  0,
                  0
                ]
              },
              "o": {
                "a": 0,
                "k": 100
              },
              "sk": {
                "a": 0,
                "k": 0
              },
              "sa": {
                "a": 0,
                "k": 0
              },
              "nm": "tr"
            }
          ],
          "np": 3,
          "cix": 2,
          "ix": 1
        }
      ],
      "ao": 0
    },
    {
      "ty": 4,
      "nm": "foot_r",
      "ind": 12,
      "ip": 0,
      "op": 36,
      "st": 0,
      "bm": 0,
      "sr": 1,
      "ks": {
        "p": {
          "a": 0,
          "k": [
            196,
            373
          ]
        },
        "r": {
          "a": 0,
          "k": 0
        },
        "a": {
          "a": 0,
          "k": [
            0,
            0
          ]
        },
        "s": {
          "a": 0,
          "k": [
            100,
            100
          ]
        },
        "o": {
          "a": 0,
          "k": 100
        }
      },
      "shapes": [
        {
          "ty": "gr",
          "nm": "f",
          "it": [
            {
              "ty": "el",
              "s": {
                "a": 0,
                "k": [
                  34,
                  14
                ]
              },
              "p": {
                "a": 0,
                "k": [
                  0,
                  0
                ]
              },
              "nm": "el",
              "d": 1
            },
            {
              "ty": "fl",
              "c": {
                "a": 0,
                "k": [
                  0.2196078431372549,
                  0.2196078431372549,
                  0.2980392156862745,
                  1.0
                ]
              },
              "o": {
                "a": 0,
                "k": 100
              },
              "r": 1,
              "nm": "fill"
            },
            {
              "ty": "tr",
              "p": {
                "a": 0,
                "k": [
                  0,
                  0
                ]
              },
              "r": {
                "a": 0,
                "k": 0
              },
              "s": {
                "a": 0,
                "k": [
                  100,
                  100
                ]
              },
              "a": {
                "a": 0,
                "k": [
                  0,
                  0
                ]
              },
              "o": {
                "a": 0,
                "k": 100
              },
              "sk": {
                "a": 0,
                "k": 0
              },
              "sa": {
                "a": 0,
                "k": 0
              },
              "nm": "tr"
            }
          ],
          "np": 3,
          "cix": 2,
          "ix": 1
        }
      ],
      "ao": 0
    },
    {
      "ty": 4,
      "nm": "foot_l",
      "ind": 13,
      "ip": 0,
      "op": 36,
      "st": 0,
      "bm": 0,
      "sr": 1,
      "ks": {
        "p": {
          "a": 0,
          "k": [
            184,
            375
          ]
        },
        "r": {
          "a": 0,
          "k": 0
        },
        "a": {
          "a": 0,
          "k": [
            0,
            0
          ]
        },
        "s": {
          "a": 0,
          "k": [
            100,
            100
          ]
        },
        "o": {
          "a": 0,
          "k": 100
        }
      },
      "shapes": [
        {
          "ty": "gr",
          "nm": "f",
          "it": [
            {
              "ty": "el",
              "s": {
                "a": 0,
                "k": [
                  30,
                  12
                ]
              },
              "p": {
                "a": 0,
                "k": [
                  0,
                  0
                ]
              },
              "nm": "el",
              "d": 1
            },
            {
              "ty": "fl",
              "c": {
                "a": 0,
                "k": [
                  0.25882352941176473,
                  0.25882352941176473,
                  0.34509803921568627,
                  1.0
                ]
              },
              "o": {
                "a": 0,
                "k": 100
              },
              "r": 1,
              "nm": "fill"
            },
            {
              "ty": "tr",
              "p": {
                "a": 0,
                "k": [
                  0,
                  0
                ]
              },
              "r": {
                "a": 0,
                "k": 0
              },
              "s": {
                "a": 0,
                "k": [
                  100,
                  100
                ]
              },
              "a": {
                "a": 0,
                "k": [
                  0,
                  0
                ]
              },
              "o": {
                "a": 0,
                "k": 100
              },
              "sk": {
                "a": 0,
                "k": 0
              },
              "sa": {
                "a": 0,
                "k": 0
              },
              "nm": "tr"
            }
          ],
          "np": 3,
          "cix": 2,
          "ix": 1
        }
      ],
      "ao": 0
    },
    {
      "ty": 4,
      "nm": "floor_line",
      "ind": 14,
      "ip": 0,
      "op": 36,
      "st": 0,
      "bm": 0,
      "sr": 1,
      "ks": {
        "p": {
          "a": 0,
          "k": [
            0,
            0
          ]
        },
        "r": {
          "a": 0,
          "k": 0
        },
        "a": {
          "a": 0,
          "k": [
            0,
            0
          ]
        },
        "s": {
          "a": 0,
          "k": [
            100,
            100
          ]
        },
        "o": {
          "a": 0,
          "k": 100
        }
      },
      "shapes": [
        {
          "ty": "gr",
          "nm": "fl",
          "it": [
            {
              "ty": "rc",
              "s": {
                "a": 0,
                "k": [
                  400,
                  2
                ]
              },
              "p": {
                "a": 0,
                "k": [
                  200,
                  375.5
                ]
              },
              "r": {
                "a": 0,
                "k": 0
              },
              "nm": "rc",
              "d": 1
            },
            {
              "ty": "fl",
              "c": {
                "a": 0,
                "k": [
                  0.22745098039215686,
                  0.3137254901960784,
                  0.5019607843137255,
                  1.0
                ]
              },
              "o": {
                "a": 0,
                "k": 100
              },
              "r": 1,
              "nm": "fill"
            },
            {
              "ty": "tr",
              "p": {
                "a": 0,
                "k": [
                  0,
                  0
                ]
              },
              "r": {
                "a": 0,
                "k": 0
              },
              "s": {
                "a": 0,
                "k": [
                  100,
                  100
                ]
              },
              "a": {
                "a": 0,
                "k": [
                  0,
                  0
                ]
              },
              "o": {
                "a": 0,
                "k": 100
              },
              "sk": {
                "a": 0,
                "k": 0
              },
              "sa": {
                "a": 0,
                "k": 0
              },
              "nm": "tr"
            }
          ],
          "np": 3,
          "cix": 2,
          "ix": 1
        }
      ],
      "ao": 0
    },
    {
      "ty": 4,
      "nm": "floor",
      "ind": 15,
      "ip": 0,
      "op": 36,
      "st": 0,
      "bm": 0,
      "sr": 1,
      "ks": {
        "p": {
          "a": 0,
          "k": [
            0,
            0
          ]
        },
        "r": {
          "a": 0,
          "k": 0
        },
        "a": {
          "a": 0,
          "k": [
            0,
            0
          ]
        },
        "s": {
          "a": 0,
          "k": [
            100,
            100
          ]
        },
        "o": {
          "a": 0,
          "k": 100
        }
      },
      "shapes": [
        {
          "ty": "gr",
          "nm": "fl",
          "it": [
            {
              "ty": "rc",
              "s": {
                "a": 0,
                "k": [
                  400,
                  26
                ]
              },
              "p": {
                "a": 0,
                "k": [
                  200,
                  388
                ]
              },
              "r": {
                "a": 0,
                "k": 0
              },
              "nm": "rc",
              "d": 1
            },
            {
              "ty": "fl",
              "c": {
                "a": 0,
                "k": [
                  0.10196078431372549,
                  0.16862745098039217,
                  0.2901960784313726,
                  1.0
                ]
              },
              "o": {
                "a": 0,
                "k": 100
              },
              "r": 1,
              "nm": "fill"
            },
            {
              "ty": "tr",
              "p": {
                "a": 0,
                "k": [
                  0,
                  0
                ]
              },
              "r": {
                "a": 0,
                "k": 0
              },
              "s": {
                "a": 0,
                "k": [
                  100,
                  100
                ]
              },
              "a": {
                "a": 0,
                "k": [
                  0,
                  0
                ]
              },
              "o": {
                "a": 0,
                "k": 100
              },
              "sk": {
                "a": 0,
                "k": 0
              },
              "sa": {
                "a": 0,
                "k": 0
              },
              "nm": "tr"
            }
          ],
          "np": 3,
          "cix": 2,
          "ix": 1
        }
      ],
      "ao": 0
    }
  ]
}